xgbauto/__init__.py
xgbauto/api.py
xgbauto/autoxgb.py
xgbauto/enums.py
xgbauto/logger.py
xgbauto/metrics.py
xgbauto/params.py
xgbauto/predict.py
xgbauto/schemas.py
xgbauto/utils.py
xgbauto/cli/__init__.py
xgbauto/cli/autoxgb.py
xgbauto/cli/predict.py
xgbauto/cli/serve.py
xgbauto/cli/train.py
autoxgbAUC-2.1.0.dist-info/LICENSE
autoxgbAUC-2.1.0.dist-info/METADATA
autoxgbAUC-2.1.0.dist-info/WHEEL
autoxgbAUC-2.1.0.dist-info/entry_points.txt
autoxgbAUC-2.1.0.dist-info/top_level.txt
autoxgbAUC-2.1.0.dist-info/RECORD
