Metadata-Version: 2.1
Name: autoxgbAUC
Version: 2.1.0
Summary: xgbauto: tuning xgboost with optuna, autoxgb with aucpr for binary classification
Home-page: https://github.vodafone.com/Ahmad-waly/xgbauto
Author: Ahmad Waly
Author-email: ahmadwaly60@gmail.com
License: Apache 2.0
Platform: linux
Platform: unix
Requires-Python: >=3.6
Requires-Dist: fastapi (==0.70.0)
Requires-Dist: numpy (==1.21.3)
Requires-Dist: optuna (==2.10.0)
Requires-Dist: pyarrow (==6.0.0)
Requires-Dist: pydantic (==1.8.2)
Requires-Dist: joblib (==1.2.0)
Requires-Dist: pandas (==1.3.4)
Requires-Dist: scikit-learn (==1.0.1)
Requires-Dist: uvicorn (==0.15.0)
Requires-Dist: xgboost (==1.5.0)
